Metadata-Version: 2.4
Name: py_ccm15
Version: 0.1.2
Summary: A package to control Midea CCM15 data converter modules
Author-email: Oscar Calvo <oscar@calvonet.com>
License-Expression: MIT
Project-URL: Homepage, https://github.com/ocalvo/py-ccm15
Keywords: Midea,CCM15,data converter
Requires-Python: >=3.7
License-File: LICENSE
Requires-Dist: httpx>=0.24.1
Requires-Dist: xmltodict>=0.13.0
Requires-Dist: aiohttp>=3.8.5
Dynamic: license-file
